[
  {
    "ContainingType": "MessageAPI.Controllers.MessagesController",
    "Method": "PostMessage",
    "RelativePath": "api/messages",
    "HttpMethod": "POST",
    "IsController": true,
    "Order": 0,
    "Parameters": [
      {
        "Name": "message",
        "Type": "MessageAPI.Models.Message",
        "IsRequired": true
      }
    ],
    "ReturnTypes": [
      {
        "Type": "MessageAPI.Models.Message",
        "MediaTypes": [
          "text/plain",
          "application/json",
          "text/json"
        ],
        "StatusCode": 200
      }
    ]
  },
  {
    "ContainingType": "MessageAPI.Controllers.MessagesController",
    "Method": "GetMessages",
    "RelativePath": "api/messages/thread/{threadId}",
    "HttpMethod": "GET",
    "IsController": true,
    "Order": 0,
    "Parameters": [
      {
        "Name": "threadId",
        "Type": "System.Int32",
        "IsRequired": true
      }
    ],
    "ReturnTypes": [
      {
        "Type": "System.Collections.Generic.IEnumerable\u00601[[MessageAPI.Models.Message, MessageAPI, Version=1.0.0.0, Culture=neutral, PublicKeyToken=null]]",
        "MediaTypes": [
          "text/plain",
          "application/json",
          "text/json"
        ],
        "StatusCode": 200
      }
    ]
  },
  {
    "ContainingType": "MessageAPI.Controllers.ThreadsController",
    "Method": "GetThreads",
    "RelativePath": "api/threads",
    "HttpMethod": "GET",
    "IsController": true,
    "Order": 0,
    "Parameters": [],
    "ReturnTypes": [
      {
        "Type": "System.Collections.Generic.IEnumerable\u00601[[MessageAPI.Models.Thread, MessageAPI, Version=1.0.0.0, Culture=neutral, PublicKeyToken=null]]",
        "MediaTypes": [
          "text/plain",
          "application/json",
          "text/json"
        ],
        "StatusCode": 200
      }
    ]
  },
  {
    "ContainingType": "MessageAPI.Controllers.ThreadsController",
    "Method": "CreateThread",
    "RelativePath": "api/threads",
    "HttpMethod": "POST",
    "IsController": true,
    "Order": 0,
    "Parameters": [
      {
        "Name": "createThreadDto",
        "Type": "MessageAPI.Dtos.CreateThreadDto",
        "IsRequired": true
      }
    ],
    "ReturnTypes": [
      {
        "Type": "MessageAPI.Models.Thread",
        "MediaTypes": [
          "text/plain",
          "application/json",
          "text/json"
        ],
        "StatusCode": 200
      }
    ]
  },
  {
    "ContainingType": "MessageAPI.Controllers.UsersController",
    "Method": "GetUsers",
    "RelativePath": "api/users",
    "HttpMethod": "GET",
    "IsController": true,
    "Order": 0,
    "Parameters": [],
    "ReturnTypes": [
      {
        "Type": "System.Collections.Generic.IEnumerable\u00601[[MessageAPI.Models.User, MessageAPI, Version=1.0.0.0, Culture=neutral, PublicKeyToken=null]]",
        "MediaTypes": [
          "text/plain",
          "application/json",
          "text/json"
        ],
        "StatusCode": 200
      }
    ]
  },
  {
    "ContainingType": "MessageAPI.Controllers.UsersController",
    "Method": "CreateUser",
    "RelativePath": "api/users",
    "HttpMethod": "POST",
    "IsController": true,
    "Order": 0,
    "Parameters": [
      {
        "Name": "user",
        "Type": "MessageAPI.Models.User",
        "IsRequired": true
      }
    ],
    "ReturnTypes": [
      {
        "Type": "MessageAPI.Models.User",
        "MediaTypes": [
          "text/plain",
          "application/json",
          "text/json"
        ],
        "StatusCode": 200
      }
    ]
  }
]